target/scala-2.12/classes/uart_core.v
`timescale 10ns/1ns
module uart_core (
    input  clk_i,
    input  rst_ni,
    
    input  ren,
    input  we,
    input  [31:0] wdata,
    output [31:0] rdata,
    input  [7:0]  addr,    
    output tx_o,
    input  rx_i,
    
    output intr_tx
);
    
    localparam ADDR_CTRL = 0;
    localparam ADDR_TX   = 4;
    localparam ADDR_RX   = 8;
    localparam RX_EN     = 12;
    localparam TX_EN     = 16;
    localparam RX_STATUS = 20;
    localparam RX_SC     = 24;
    
    reg [15:0] control;
    reg [7:0]  tx;
    wire [7:0] rx;
    reg  [7:0] rx_reg;
    reg        rx_en;
    reg        tx_en;
    reg        rx_status;
    reg        rx_clr;
    wire       rx_done; 
  
  localparam IDLE         = 3'b000;     //waits for tx_en signal to be high else no operation is performed
  localparam TX_START_BIT = 3'b001;     //start bit is sent in this state
  localparam TX_DATA_BITS = 3'b010;     //data bits are transfered in this state
  localparam TX_STOP_BIT  = 3'b011;     //stop bit is sent in this state, which shows that the data is transfered
  localparam CLEANUP      = 3'b100;     //tx_done signal set to high and moves back to idle state
  
  reg [2:0] r_SM_Main     ;     //contains all the states
  reg [15:0] r_Clock_Count ;    //counts the number of clocks
  reg [2:0] r_Bit_Index   ;     //tells the index of data
  reg [7:0] r_TX_Data     ;     //data is transfered from i_TX_byte to r_TX_data buffer
  reg       r_TX_Done     ;     //this signal is high when the transfer is done 
 

   wire       i_Rx_Serial;                 //serial input
   wire [15:0] CLKS_PER_BIT;               
   wire        o_Rx_DV;                    //high when the data is recieved
   wire  [7:0] o_Rx_Byte ;                  //Outputs Data recieved



////////////////
    wire [7:0] i_TX_Byte; //contains the data to be transfered
   //output      o_TX_Active,
    reg  o_TX_Serial; //outputs the data serially
    wire     o_TX_Done ; //this signal is high when the transfer is done


  parameter s_IDLE         = 3'b000;              //First state i.e. IDLE
  parameter s_RX_START_BIT = 3'b001;              //Second state i.e. START_BIT
  parameter s_RX_DATA_BITS = 3'b010;              //Third state i.e. DATA_BITS
  parameter s_RX_STOP_BIT  = 3'b011;              //Fourth state i.e. STOP_BIT
  parameter s_CLEANUP      = 3'b100;              //Fifth state i.e. CLEANUP
   
  reg           r_Rx_Data_R ;                 
  reg           r_Rx_Data   ;
   
 
  reg [7:0]     r_Rx_Byte   ;
  reg           r_Rx_DV     ;

////////////////////////////////////
 
 assign i_TX_Byte = tx;             //
 assign tx_o =  o_TX_Serial ;        ///
 assign intr_tx = o_TX_Done ;        ///

    

 
  
//  reg       r_TX_Active   ;
    
  always @(posedge clk_i)
  begin
    if(~rst_ni) begin     //if reset = 0 then all the signals will be reset
        r_SM_Main     <= 3'b0;
        r_Clock_Count <= 16'b0;
        r_Bit_Index   <= 3'b0;
        r_TX_Data     <= 8'b0;
        r_TX_Done     <= 1'b0;
       // r_TX_Active   = 0;
    end else begin        //if reset = 1 then other operations will be performed
    case (r_SM_Main)      
      IDLE :
        begin
          o_TX_Serial   <= 1'b1;         // Drive Line High for Idle
          r_TX_Done     <= 1'b0;          
          r_Clock_Count <= 16'b0;
          r_Bit_Index   <= 3'b0;
          
          if (tx_en == 1'b1)        //if transfer is enabled 
          begin
           // r_TX_Active <= 1'b1;
            r_TX_Data   <= i_TX_Byte;     //data is transfered to register
            r_SM_Main   <= TX_START_BIT;  //after tx_en is high state will move to START_BIT state
          end
          else          //if tx_en = 0
            r_SM_Main <= IDLE;  //it will jump to IDLE state 
        end // case: IDLE
      
      
      // Send out Start Bit. Start bit = 0
      TX_START_BIT :
        begin
          o_TX_Serial <= 1'b0;      //sends start bit which is equal to 0 , to start the transfer of data
          
          // Wait CLKS_PER_BIT-1 clock cycles for start bit to finish
          if (r_Clock_Count < CLKS_PER_BIT-1)   
          begin
            r_Clock_Count <= r_Clock_Count + 16'b1; //increment in clock count till the condition breaks
            r_SM_Main     <= TX_START_BIT;    //jumps backs to state START_BIT until start bit is finished
          end
          else
          begin
            r_Clock_Count <= 16'b0;   //resets the counter
            r_SM_Main     <= TX_DATA_BITS;    //jumps to DATA_BITS state,where the data is transfered
          end
        end // case: TX_START_BIT
      
      
      // Wait CLKS_PER_BIT-1 clock cycles for data bits to finish         
      TX_DATA_BITS :
        begin
          o_TX_Serial <= r_TX_Data[r_Bit_Index];  //sends the data to output one by one
          
          if (r_Clock_Count < CLKS_PER_BIT-16'b1)
          begin
            r_Clock_Count <= r_Clock_Count + 16'b1; //increment in clock count till the condition breaks
            r_SM_Main     <= TX_DATA_BITS;  //jumps backs to state START_BIT until 1 bit is sent completely
          end
          else    //when 1 bit is sent
          begin
            r_Clock_Count <= 3'b0;  //resets the counter
            
            // Check if we have sent out all bits
            if (r_Bit_Index < 7)  //total index of the register containing data
            begin
              r_Bit_Index <= r_Bit_Index + 3'b1;    //increment in index, so next bit can be transfered
              r_SM_Main   <= TX_DATA_BITS;    //move back to state DATA_BITS to transfer next bit
            end
            else    //when all the bits are transfered
            begin
              r_Bit_Index <= 3'b0;    //reset the index
              r_SM_Main   <= TX_STOP_BIT;   //as all the bits are transfered
            end
          end 
        end // case: TX_DATA_BITS
      
      
      // Send out Stop bit.  Stop bit = 1
      TX_STOP_BIT :
        begin
          o_TX_Serial <= 1'b1;      //sents the stop bit,which show that the data is transfered
          
          // Wait CLKS_PER_BIT-1 clock cycles for Stop bit to finish
          if (r_Clock_Count < CLKS_PER_BIT- 16'b1)
          begin
            r_Clock_Count <= r_Clock_Count + 16'b1;
            r_SM_Main     <= TX_STOP_BIT;
          end
          else
          begin
            r_TX_Done     <= 1'b1;  //this signal is high when the transfer is done
            r_Clock_Count <= 16'b0; //reset the clock count
            r_SM_Main     <= CLEANUP; //move to CLEANUP state
           // r_TX_Active   <= 1'b0;
          end 
        end // case: TX_STOP_BIT
      
      
      // Stay here 1 clock
      CLEANUP :
      begin
          r_TX_Done <= 1'b1;  
          r_SM_Main <= IDLE;    //sent to idle state, to clear the registers
        end
      
      
      default :
        r_SM_Main <= IDLE;  //is none of the case is select,default case is IDLE
      
    endcase
    end 
  end
  
  //assign o_TX_Active = r_TX_Active;
  assign o_TX_Done   = r_TX_Done;     //r_TX_DONE signal is transfered to the output pin.
  
//////////////////



  

  assign i_Rx_Serial = rx_en? rx_i: 1'b1 ;  //
  assign rx_done =  o_Rx_DV;//
  assign CLKS_PER_BIT = control;//
  assign rx =   o_Rx_Byte;//






   
  // Purpose: Double-register the incoming data.
  // This allows it to be used in the UART RX Clock Domain.
  // (It removes problems caused by metastability)
  always @(posedge clk_i)
    begin
    if (~rst_ni) begin                            //when reset = 0, it reset the registers as reset is active low 
      r_Rx_Data_R <= 1'b1;                        
      r_Rx_Data   <= 1'b1;
    end else begin                                //if reset = 1
      r_Rx_Data_R <= i_Rx_Serial;                 //1st bit is trasnferd in buffer
      r_Rx_Data   <= r_Rx_Data_R;                 
    end
  end
   
   
  // Purpose: Control RX state machine
  always @(posedge clk_i or negedge rst_ni)
    begin
      if (~rst_ni) begin                          //if reset = 0 
        r_SM_Main <= s_IDLE;                      //Starts jumps to IDLE
        r_Rx_DV       <= 1'b0;                    //Done signal resets
        r_Clock_Count <= 16'b0;                   //Clock count resets
        r_Bit_Index   <= 3'b0;                    //resets index
	      r_Rx_Byte     <= 8'b0;            
      end else begin                              //when reset = 1
      case (r_SM_Main)                            
        s_IDLE :
          begin
            r_Rx_DV       <= 1'b0;                
            r_Clock_Count <= 16'b0;
            r_Bit_Index   <= 3'b0;
            r_Rx_Byte     <= 8'b0; 
            if (r_Rx_Data == 1'b0)                 // Start bit detected
              r_SM_Main <= s_RX_START_BIT;         //state change to START_BIT
            else
              r_SM_Main <= s_IDLE;                //if start bit is detected, state jumps back to IDLE
          end
         
        // Check middle of start bit to make sure it's still low
        s_RX_START_BIT :
          begin
            if (r_Clock_Count == ((CLKS_PER_BIT-1)>>1))   //shifts 1 bit towards right i.e. divide by two , to check the middle of start bit if it's still low 
              begin
                if (r_Rx_Data == 1'b0)                    //start bit detected i.e. equal to 0
                  begin
                    r_Clock_Count <= 16'b0;               // reset counter, found the middle
                    r_SM_Main     <= s_RX_DATA_BITS;      //when start bit is detected,state shifts to  DATA_BITS
                  end
                else
                  r_SM_Main <= s_IDLE;                    //If start bit is not there,then it jumps back to IDLE state 31
              end
            else
              begin
                r_Clock_Count <= r_Clock_Count + 16'b1;   //increment in clock count until the middle of the start bit
                r_SM_Main     <= s_RX_START_BIT;          //jumps to start bit until the middle of start bit
              end
          end // case: s_RX_START_BIT
         
         
        // Wait CLKS_PER_BIT-1 clock cycles to sample serial data
        s_RX_DATA_BITS :                                  
          begin
            if (r_Clock_Count < CLKS_PER_BIT-1)           
              begin
                r_Clock_Count <= r_Clock_Count + 16'b1;    //Increments clock counts until next bit 
                r_SM_Main     <= s_RX_DATA_BITS;           //jumps to state bit until next bit
              end
            else                                           
              begin
                r_Clock_Count          <= 16'b0;           //when 1 bit recieved, it reset the clock count
                r_Rx_Byte[r_Bit_Index] <= r_Rx_Data;       //transfers the serial bit
                 
                // Check if we have received all bits
                if (r_Bit_Index < 7)                      //as 8 bit have to be transfered
                  begin
                    r_Bit_Index <= r_Bit_Index + 3'b1;      //increment in index till 8 bits are transfered
                    r_SM_Main   <= s_RX_DATA_BITS;          //jump back to DATA_BIT state till all the bits are transfered
                  end
                else
                  begin
                    r_Bit_Index <= 3'b0;                    //resets index
                    r_SM_Main   <= s_RX_STOP_BIT;           //jump to STOP_BIT state
                  end
              end
          end // case: s_RX_DATA_BITS
     
     
        // Receive Stop bit.  Stop bit = 1
        s_RX_STOP_BIT :
          begin
            // Wait CLKS_PER_BIT-1 clock cycles for Stop bit to finish
            if (r_Clock_Count < CLKS_PER_BIT-1)
              begin
                r_Clock_Count <= r_Clock_Count + 16'b1;       //increment till the stop bit finishes
                r_SM_Main     <= s_RX_STOP_BIT;               //jumps back to STOP_BIT state
              end
            else
              begin
                r_Rx_DV       <= 1'b1;                      //once the data is recieved this signal is high
                r_Clock_Count <= 16'b0;                     //clock count resets once the data is recived
                r_SM_Main     <= s_CLEANUP;                 //jumps to CLEANUP state
              end
          end // case: s_RX_STOP_BIT
     
         
        // Stay here 1 clock
        s_CLEANUP :
          begin
            r_SM_Main <= s_IDLE;                          //jumps back to IDLE state to reset the registers
            r_Rx_DV   <= 1'b0;                            //resets the signal after one cycle
          end
         
         
        default :
          r_SM_Main <= s_IDLE;                            //Default state is set to IDLE
         
      endcase
      end
    end   
   
  assign o_Rx_DV   = r_Rx_DV;                              //signal outputs from register to output pin
  assign o_Rx_Byte = r_Rx_Byte;                            //data outputs from register to output pin
   













    
    always @(posedge clk_i or negedge rst_ni) begin
        if(~rst_ni) begin
            control <= 16'b0;
            tx      <= 8'b0;
            rx_en   <= 1'b0;
            tx_en   <= 1'b0;
	        rx_clr  <= 1'b1;
        end else begin
          if(~ren & we) begin
            if(addr == ADDR_CTRL) begin
                control  <= wdata[15:0];
            end else if (addr == ADDR_TX) begin
                tx  <= wdata[7:0];
            end else if (addr == RX_EN) begin
                rx_en <= wdata[0];
            end else if(addr == TX_EN) begin
                tx_en <= wdata[0];
            end else if(addr == RX_SC) begin
	            rx_clr <= wdata[0];
	    end else begin
                control <= 16'b0;
                tx      <= 8'b0;
                rx_en   <= 1'b0;
                tx_en   <= 1'b0;
		        rx_clr  <= 1'b1;
            end
        end 
    end     
  end
    
 


always @(posedge clk_i or negedge rst_ni) begin
    if(!rst_ni) begin
        rx_status <= 1'b0;
    	rx_reg    <= 8'b0;
    end else begin
        
	if (rx_done) begin
	   rx_reg  <= rx;
	   rx_status <= 1'b1;	
	end else if(!rx_clr) begin
	   rx_status <= 1'b0;	
	end
    end
end
  
 assign rdata = (addr == 20)? rx_status : (addr == 8)? rx_reg : 0;   





      
   
endmodule

test_run_dir/UART_TEST/UART_CORE.v
module UART_CORE(
  input         clock,
  input         reset,
  input         io_ren,
  input         io_we,
  input  [31:0] io_wdata,
  input  [7:0]  io_addr,
  input         io_rx_i,
  output [31:0] io_rdata,
  output        io_tx_o,
  output        io_intr_tx
);
  wire  u_core_clk_i; // @[UART_CORE.scala 41:22]
  wire  u_core_rst_ni; // @[UART_CORE.scala 41:22]
  wire  u_core_ren; // @[UART_CORE.scala 41:22]
  wire  u_core_we; // @[UART_CORE.scala 41:22]
  wire [31:0] u_core_wdata; // @[UART_CORE.scala 41:22]
  wire [7:0] u_core_addr; // @[UART_CORE.scala 41:22]
  wire  u_core_rx_i; // @[UART_CORE.scala 41:22]
  wire [31:0] u_core_rdata; // @[UART_CORE.scala 41:22]
  wire  u_core_tx_o; // @[UART_CORE.scala 41:22]
  wire  u_core_intr_tx; // @[UART_CORE.scala 41:22]
  uart_core u_core ( // @[UART_CORE.scala 41:22]
    .clk_i(u_core_clk_i),
    .rst_ni(u_core_rst_ni),
    .ren(u_core_ren),
    .we(u_core_we),
    .wdata(u_core_wdata),
    .addr(u_core_addr),
    .rx_i(u_core_rx_i),
    .rdata(u_core_rdata),
    .tx_o(u_core_tx_o),
    .intr_tx(u_core_intr_tx)
  );
  assign io_rdata = u_core_rdata; // @[UART_CORE.scala 56:12]
  assign io_tx_o = u_core_tx_o; // @[UART_CORE.scala 57:11]
  assign io_intr_tx = u_core_intr_tx; // @[UART_CORE.scala 58:14]
  assign u_core_clk_i = ~clock; // @[UART_CORE.scala 46:22]
  assign u_core_rst_ni = ~reset; // @[UART_CORE.scala 47:23]
  assign u_core_ren = io_ren; // @[UART_CORE.scala 50:17]
  assign u_core_we = io_we; // @[UART_CORE.scala 51:16]
  assign u_core_wdata = io_wdata; // @[UART_CORE.scala 52:19]
  assign u_core_addr = io_addr; // @[UART_CORE.scala 53:18]
  assign u_core_rx_i = io_rx_i; // @[UART_CORE.scala 54:18]
endmodule

test_run_dir/UART_TEST/UART_CORE.vcd
$version Generated by VerilatedVcd $end
$date Wed Sep 29 16:44:58 2021
 $end
$timescale   1ns $end

 $scope module TOP $end
  $var wire  1 6 clock $end
  $var wire  8 ; io_addr [7:0] $end
  $var wire  1 ? io_intr_tx $end
  $var wire 32 = io_rdata [31:0] $end
  $var wire  1 8 io_ren $end
  $var wire  1 < io_rx_i $end
  $var wire  1 > io_tx_o $end
  $var wire 32 : io_wdata [31:0] $end
  $var wire  1 9 io_we $end
  $var wire  1 7 reset $end
  $scope module UART_CORE $end
   $var wire  1 6 clock $end
   $var wire  8 ; io_addr [7:0] $end
   $var wire  1 ? io_intr_tx $end
   $var wire 32 = io_rdata [31:0] $end
   $var wire  1 8 io_ren $end
   $var wire  1 < io_rx_i $end
   $var wire  1 > io_tx_o $end
   $var wire 32 : io_wdata [31:0] $end
   $var wire  1 9 io_we $end
   $var wire  1 7 reset $end
   $var wire  8 ; u_core_addr [7:0] $end
   $var wire  1 # u_core_clk_i $end
   $var wire  1 * u_core_intr_tx $end
   $var wire 32 @ u_core_rdata [31:0] $end
   $var wire  1 8 u_core_ren $end
   $var wire  1 $ u_core_rst_ni $end
   $var wire  1 < u_core_rx_i $end
   $var wire  1 ) u_core_tx_o $end
   $var wire 32 : u_core_wdata [31:0] $end
   $var wire  1 9 u_core_we $end
   $scope module u_core $end
    $var wire 32 B ADDR_CTRL [31:0] $end
    $var wire 32 D ADDR_RX [31:0] $end
    $var wire 32 C ADDR_TX [31:0] $end
    $var wire  3 M CLEANUP [2:0] $end
    $var wire 16 . CLKS_PER_BIT [15:0] $end
    $var wire  3 I IDLE [2:0] $end
    $var wire 32 E RX_EN [31:0] $end
    $var wire 32 H RX_SC [31:0] $end
    $var wire 32 G RX_STATUS [31:0] $end
    $var wire  3 K TX_DATA_BITS [2:0] $end
    $var wire 32 F TX_EN [31:0] $end
    $var wire  3 J TX_START_BIT [2:0] $end
    $var wire  3 L TX_STOP_BIT [2:0] $end
    $var wire  8 ; addr [7:0] $end
    $var wire  1 # clk_i $end
    $var wire 16 . control [15:0] $end
    $var wire  1 A i_Rx_Serial $end
    $var wire  8 / i_TX_Byte [7:0] $end
    $var wire  1 * intr_tx $end
    $var wire  8 % o_Rx_Byte [7:0] $end
    $var wire  1 ( o_Rx_DV $end
    $var wire  1 * o_TX_Done $end
    $var wire  1 ) o_TX_Serial $end
    $var wire  3 5 r_Bit_Index [2:0] $end
    $var wire 16 4 r_Clock_Count [15:0] $end
    $var wire  8 % r_Rx_Byte [7:0] $end
    $var wire  1 ( r_Rx_DV $end
    $var wire  1 - r_Rx_Data $end
    $var wire  1 , r_Rx_Data_R $end
    $var wire  3 3 r_SM_Main [2:0] $end
    $var wire  8 + r_TX_Data [7:0] $end
    $var wire  1 * r_TX_Done $end
    $var wire 32 @ rdata [31:0] $end
    $var wire  1 8 ren $end
    $var wire  1 $ rst_ni $end
    $var wire  8 % rx [7:0] $end
    $var wire  1 2 rx_clr $end
    $var wire  1 ( rx_done $end
    $var wire  1 0 rx_en $end
    $var wire  1 < rx_i $end
    $var wire  8 & rx_reg [7:0] $end
    $var wire  1 ' rx_status $end
    $var wire  3 M s_CLEANUP [2:0] $end
    $var wire  3 I s_IDLE [2:0] $end
    $var wire  3 K s_RX_DATA_BITS [2:0] $end
    $var wire  3 J s_RX_START_BIT [2:0] $end
    $var wire  3 L s_RX_STOP_BIT [2:0] $end
    $var wire  8 / tx [7:0] $end
    $var wire  1 1 tx_en $end
    $var wire  1 ) tx_o $end
    $var wire 32 : wdata [31:0] $end
    $var wire  1 9 we $end
   $upscope $end
  $upscope $end
 $upscope $end
$enddefinitions $end


#0
1#
0$
b00000000 %
b00000000 &
0'
0(
0)
0*
b00000000 +
1,
1-
b0000000000000000 .
b00000000 /
00
01
12
b000 3
b0000000000000000 4
b000 5
06
17
08
09
b00000000000000000000000000000000 :
b00000000 ;
0<
b00000000000000000000000000000000 =
0>
0?
b00000000000000000000000000000000 @
1A
b00000000000000000000000000000000 B
b00000000000000000000000000000100 C
b00000000000000000000000000001000 D
b00000000000000000000000000001100 E
b00000000000000000000000000010000 F
b00000000000000000000000000010100 G
b00000000000000000000000000011000 H
b000 I
b001 J
b010 K
b011 L
b100 M
#1
0#
16
#2
1#
1$
06
07
#3
0#
16
#4
1#
1)
06
1>
#5
0#
16
#6
1#
06
b00000000000000000000000001010111 :
#7
0#
16
#8
1#
b0000000001010111 .
06
19
#9
0#
16
#10
1#
06
09
#11
0#
16
#12
1#
06
b00000100 ;
#13
0#
16
#14
1#
06
b00000000000000000000000010101010 :
#15
0#
16
#16
1#
b10101010 /
06
19
#17
0#
16
#18
1#
06
09
#19
0#
16
#20
1#
06
b00010000 ;
#21
0#
16
#22
1#
06
b00000000000000000000000000000001 :
#23
0#
16
#24
1#
11
06
19
#25
0#
16
#26
1#
b10101010 +
b001 3
06
09
#27
0#
16
#28
1#
0)
b0000000000000001 4
06
0>
#29
0#
16
#30
1#
b0000000000000010 4
06
b00000000000000000000000000000000 :
#31
0#
16
#32
1#
01
b0000000000000011 4
06
19
#33
0#
16
#34
1#
b0000000000000100 4
06
09
#35
0#
16
#36
1#
b0000000000000101 4
06
#37
0#
16
#38
1#
b0000000000000110 4
06
#39
0#
16
#40
1#
b0000000000000111 4
06
#41
0#
16
#42
1#
b0000000000001000 4
06
#43
0#
16
#44
1#
b0000000000001001 4
06
#45
0#
16
#46
1#
b0000000000001010 4
06
#47
0#
16
#48
1#
b0000000000001011 4
06
#49
0#
16
#50
1#
b0000000000001100 4
06
#51
0#
16
#52
1#
b0000000000001101 4
06
#53
0#
16
#54
1#
b0000000000001110 4
06
#55
0#
16
#56
1#
b0000000000001111 4
06
#57
0#
16
#58
1#
b0000000000010000 4
06
#59
0#
16
#60
1#
b0000000000010001 4
06
#61
0#
16
#62
1#
b0000000000010010 4
06
#63
0#
16
#64
1#
b0000000000010011 4
06
#65
0#
16
#66
1#
b0000000000010100 4
06
#67
0#
16
#68
1#
b0000000000010101 4
06
#69
0#
16
#70
1#
b0000000000010110 4
06
#71
0#
16
#72
1#
b0000000000010111 4
06
#73
0#
16
#74
1#
b0000000000011000 4
06
#75
0#
16
#76
1#
b0000000000011001 4
06
#77
0#
16
#78
1#
b0000000000011010 4
06
#79
0#
16
#80
1#
b0000000000011011 4
06
#81
0#
16
#82
1#
b0000000000011100 4
06
#83
0#
16
#84
1#
b0000000000011101 4
06
#85
0#
16
#86
1#
b0000000000011110 4
06
#87
0#
16
#88
1#
b0000000000011111 4
06
#89
0#
16
#90
1#
b0000000000100000 4
06
#91
0#
16
#92
1#
b0000000000100001 4
06
#93
0#
16
#94
1#
b0000000000100010 4
06
#95
0#
16
#96
1#
b0000000000100011 4
06
#97
0#
16
#98
1#
b0000000000100100 4
06
#99
0#
16
#100
1#
b0000000000100101 4
06
#101
0#
16
#102
1#
b0000000000100110 4
06
#103
0#
16
#104
1#
b0000000000100111 4
06
#105
0#
16
#106
1#
b0000000000101000 4
06
#107
0#
16
#108
1#
b0000000000101001 4
06
#109
0#
16
#110
1#
b0000000000101010 4
06
#111
0#
16
#112
1#
b0000000000101011 4
06
#113
0#
16
#114
1#
b0000000000101100 4
06
#115
0#
16
#116
1#
b0000000000101101 4
06
#117
0#
16
#118
1#
b0000000000101110 4
06
#119
0#
16
#120
1#
b0000000000101111 4
06
#121
0#
16
#122
1#
b0000000000110000 4
06
#123
0#
16
#124
1#
b0000000000110001 4
06
#125
0#
16
#126
1#
b0000000000110010 4
06
#127
0#
16
#128
1#
b0000000000110011 4
06
#129
0#
16
#130
1#
b0000000000110100 4
06
#131
0#
16
#132
1#
b0000000000110101 4
06
#133
0#
16
#134
1#
b0000000000110110 4
06
#135
0#
16
#136
1#
b0000000000110111 4
06
#137
0#
16
#138
1#
b0000000000111000 4
06
#139
0#
16
#140
1#
b0000000000111001 4
06
#141
0#
16
#142
1#
b0000000000111010 4
06
#143
0#
16
#144
1#
b0000000000111011 4
06
#145
0#
16
#146
1#
b0000000000111100 4
06
#147
0#
16
#148
1#
b0000000000111101 4
06
#149
0#
16
#150
1#
b0000000000111110 4
06
#151
0#
16
#152
1#
b0000000000111111 4
06
#153
0#
16
#154
1#
b0000000001000000 4
06
#155
0#
16
#156
1#
b0000000001000001 4
06
#157
0#
16
#158
1#
b0000000001000010 4
06
#159
0#
16
#160
1#
b0000000001000011 4
06
#161
0#
16
#162
1#
b0000000001000100 4
06
#163
0#
16
#164
1#
b0000000001000101 4
06
#165
0#
16
#166
1#
b0000000001000110 4
06
#167
0#
16
#168
1#
b0000000001000111 4
06
#169
0#
16
#170
1#
b0000000001001000 4
06
#171
0#
16
#172
1#
b0000000001001001 4
06
#173
0#
16
#174
1#
b0000000001001010 4
06
#175
0#
16
#176
1#
b0000000001001011 4
06
#177
0#
16
#178
1#
b0000000001001100 4
06
#179
0#
16
#180
1#
b0000000001001101 4
06
#181
0#
16
#182
1#
b0000000001001110 4
06
#183
0#
16
#184
1#
b0000000001001111 4
06
#185
0#
16
#186
1#
b0000000001010000 4
06
#187
0#
16
#188
1#
b0000000001010001 4
06
#189
0#
16
#190
1#
b0000000001010010 4
06
#191
0#
16
#192
1#
b0000000001010011 4
06
#193
0#
16
#194
1#
b0000000001010100 4
06
#195
0#
16
#196
1#
b0000000001010101 4
06
#197
0#
16
#198
1#
b0000000001010110 4
06
#199
0#
16
#200
1#
b010 3
b0000000000000000 4
06
#201
0#
16
#202
1#
b0000000000000001 4
06
#203
0#
16
#204
1#
b0000000000000010 4
06
#205
0#
16
#206
1#
b0000000000000011 4
06
#207
0#
16
#208
1#
b0000000000000100 4
06
#209
0#
16
#210
1#
b0000000000000101 4
06
#211
0#
16
#212
1#
b0000000000000110 4
06
#213
0#
16
#214
1#
b0000000000000111 4
06
#215
0#
16
#216
1#
b0000000000001000 4
06
#217
0#
16
#218
1#
b0000000000001001 4
06
#219
0#
16
#220
1#
b0000000000001010 4
06
#221
0#
16
#222
1#
b0000000000001011 4
06
#223
0#
16
#224
1#
b0000000000001100 4
06
#225
0#
16
#226
1#
b0000000000001101 4
06
#227
0#
16
#228
1#
b0000000000001110 4
06
#229
0#
16
#230
1#
b0000000000001111 4
06
#231
0#
16
#232
1#
b0000000000010000 4
06
#233
0#
16
#234
1#
b0000000000010001 4
06
#235
0#
16
#236
1#
b0000000000010010 4
06
#237
0#
16
#238
1#
b0000000000010011 4
06
#239
0#
16
#240
1#
b0000000000010100 4
06
#241
0#
16
#242
1#
b0000000000010101 4
06
#243
0#
16
#244
1#
b0000000000010110 4
06
#245
0#
16
#246
1#
b0000000000010111 4
06
#247
0#
16
#248
1#
b0000000000011000 4
06
#249
0#
16
#250
1#
b0000000000011001 4
06
#251
0#
16
#252
1#
b0000000000011010 4
06
#253
0#
16
#254
1#
b0000000000011011 4
06
#255
0#
16
#256
1#
b0000000000011100 4
06
#257
0#
16
#258
1#
b0000000000011101 4
06
#259
0#
16
#260
1#
b0000000000011110 4
06
#261
0#
16
#262
1#
b0000000000011111 4
06
#263
0#
16
#264
1#
b0000000000100000 4
06
#265
0#
16
#266
1#
b0000000000100001 4
06
#267
0#
16
#268
1#
b0000000000100010 4
06
#269
0#
16
#270
1#
b0000000000100011 4
06
#271
0#
16
#272
1#
b0000000000100100 4
06
#273
0#
16
#274
1#
b0000000000100101 4
06
#275
0#
16
#276
1#
b0000000000100110 4
06
#277
0#
16
#278
1#
b0000000000100111 4
06
#279
0#
16
#280
1#
b0000000000101000 4
06
#281
0#
16
#282
1#
b0000000000101001 4
06
#283
0#
16
#284
1#
b0000000000101010 4
06
#285
0#
16
#286
1#
b0000000000101011 4
06
#287
0#
16
#288
1#
b0000000000101100 4
06
#289
0#
16
#290
1#
b0000000000101101 4
06
#291
0#
16
#292
1#
b0000000000101110 4
06
#293
0#
16
#294
1#
b0000000000101111 4
06
#295
0#
16
#296
1#
b0000000000110000 4
06
#297
0#
16
#298
1#
b0000000000110001 4
06
#299
0#
16
#300
1#
b0000000000110010 4
06
#301
0#
16
#302
1#
b0000000000110011 4
06
#303
0#
16
#304
1#
b0000000000110100 4
06
#305
0#
16
#306
1#
b0000000000110101 4
06
#307
0#
16
#308
1#
b0000000000110110 4
06
#309
0#
16
#310
1#
b0000000000110111 4
06
#311
0#
16
#312
1#
b0000000000111000 4
06
#313
0#
16
#314
1#
b0000000000111001 4
06
#315
0#
16
#316
1#
b0000000000111010 4
06
#317
0#
16
#318
1#
b0000000000111011 4
06
#319
0#
16
#320
1#
b0000000000111100 4
06
#321
0#
16
#322
1#
b0000000000111101 4
06
#323
0#
16
#324
1#
b0000000000111110 4
06
#325
0#
16
#326
1#
b0000000000111111 4
06
#327
0#
16
#328
1#
b0000000001000000 4
06
#329
0#
16
#330
1#
b0000000001000001 4
06
#331
0#
16
#332
1#
b0000000001000010 4
06
#333
0#
16
#334
1#
b0000000001000011 4
06
#335
0#
16
#336
1#
b0000000001000100 4
06
#337
0#
16
#338
1#
b0000000001000101 4
06
#339
0#
16
#340
1#
b0000000001000110 4
06
#341
0#
16
#342
1#
b0000000001000111 4
06
#343
0#
16
#344
1#
b0000000001001000 4
06
#345
0#
16
#346
1#
b0000000001001001 4
06
#347
0#
16
#348
1#
b0000000001001010 4
06
#349
0#
16
#350
1#
b0000000001001011 4
06
#351
0#
16
#352
1#
b0000000001001100 4
06
#353
0#
16
#354
1#
b0000000001001101 4
06
#355
0#
16
#356
1#
b0000000001001110 4
06
#357
0#
16
#358
1#
b0000000001001111 4
06
#359
0#
16
#360
1#
b0000000001010000 4
06
#361
0#
16
#362
1#
b0000000001010001 4
06
#363
0#
16
#364
1#
b0000000001010010 4
06
#365
0#
16
#366
1#
b0000000001010011 4
06
#367
0#
16
#368
1#
b0000000001010100 4
06
#369
0#
16
#370
1#
b0000000001010101 4
06
#371
0#
16
#372
1#
b0000000001010110 4
06
#373
0#
16
#374
1#
b00000001 %
b0000000000000000 4
b001 5
06
#375
0#
16
#376
1#
1)
b0000000000000001 4
06
1>
#377
0#
16
#378
1#
b0000000000000010 4
06
#379
0#
16
#380
1#
b0000000000000011 4
06
#381
0#
16
#382
1#
b0000000000000100 4
06
#383
0#
16
#384
1#
b0000000000000101 4
06
#385
0#
16
#386
1#
b0000000000000110 4
06
#387
0#
16
#388
1#
b0000000000000111 4
06
#389
0#
16
#390
1#
b0000000000001000 4
06
#391
0#
16
#392
1#
b0000000000001001 4
06
#393
0#
16
#394
1#
b0000000000001010 4
06
#395
0#
16
#396
1#
b0000000000001011 4
06
#397
0#
16
#398
1#
b0000000000001100 4
06
#399
0#
16
#400
1#
b0000000000001101 4
06
#401
0#
16
#402
1#
b0000000000001110 4
06
#403
0#
16
#404
1#
b0000000000001111 4
06
#405
0#
16
#406
1#
b0000000000010000 4
06
#407
0#
16
#408
1#
b0000000000010001 4
06
#409
0#
16
#410
1#
b0000000000010010 4
06
#411
0#
16
#412
1#
b0000000000010011 4
06
#413
0#
16
#414
1#
b0000000000010100 4
06
#415
0#
16
#416
1#
b0000000000010101 4
06
#417
0#
16
#418
1#
b0000000000010110 4
06
#419
0#
16
#420
1#
b0000000000010111 4
06
#421
0#
16
#422
1#
b0000000000011000 4
06
#423
0#
16
#424
1#
b0000000000011001 4
06
#425
0#
16
#426
1#
b0000000000011010 4
06
#427
0#
16
#428
1#
b0000000000011011 4
06
#429
0#
16
#430
1#
b0000000000011100 4
06
#431
0#
16
#432
1#
b0000000000011101 4
06
#433
0#
16
#434
1#
b0000000000011110 4
06
#435
0#
16
#436
1#
b0000000000011111 4
06
#437
0#
16
#438
1#
b0000000000100000 4
06
#439
0#
16
#440
1#
b0000000000100001 4
06
#441
0#
16
#442
1#
b0000000000100010 4
06
#443
0#
16
#444
1#
b0000000000100011 4
06
#445
0#
16
#446
1#
b0000000000100100 4
06
#447
0#
16
#448
1#
b0000000000100101 4
06
#449
0#
16
#450
1#
b0000000000100110 4
06
#451
0#
16
#452
1#
b0000000000100111 4
06
#453
0#
16
